jprofile/__init__.py
jprofile/__main__.py
jprofile/config.py
jprofile/jprofile.py
jprofile/profiles/kb_300Colour_2014.xml
jprofile/profiles/kb_300Gray_2014.xml
jprofile/profiles/kb_600Colour_2014.xml
jprofile/profiles/kb_600Gray_2014.xml
jprofile/profiles/kb_generic_2014.xml
jprofile/profiles/test.xml
jprofile/schemas/access300Colour_2014.sch
jprofile/schemas/access300Gray_2014.sch
jprofile/schemas/access600Colour_2014.sch
jprofile/schemas/access600Gray_2014.sch
jprofile/schemas/kbAccess_2014.sch
jprofile/schemas/kbMaster_2014.sch
jprofile/schemas/master300Colour_2014.sch
jprofile/schemas/master300Gray_2014.sch
jprofile/schemas/master600Colour_2014.sch
jprofile/schemas/master600Gray_2014.sch
jprofile-0.9.0.dist-info/LICENSE
jprofile-0.9.0.dist-info/METADATA
jprofile-0.9.0.dist-info/WHEEL
jprofile-0.9.0.dist-info/entry_points.txt
jprofile-0.9.0.dist-info/top_level.txt
jprofile-0.9.0.dist-info/RECORD
