Metadata-Version: 2.1
Name: jprofile
Version: 0.9.0
Summary: Automated JP2 profiling for digitisation batches
Home-page: https://github.com/KBNLresearch/jprofile
Author: Johan van der Knijff
Author-email: johan.vanderknijff@kb.nl
Maintainer: Johan van der Knijff
Maintainer-email: johan.vanderknijff@kb.nl
License: LGPL
Download-URL: https://github.com/KBNLresearch/jprofile/archive/0.9.0.tar.gz
Platform: POSIX
Platform: Windows
Classifier: Environment :: Console
Classifier: Programming Language :: Python :: 2
Classifier: Programming Language :: Python :: 2.7
Classifier: Programming Language :: Python :: 3
Requires-Python: >=3.2, <4
Requires-Dist: jpylyzer (>=2.0.0)
Requires-Dist: lxml
Requires-Dist: setuptools
